jpegger/__init__.py
jpegger/converter.py
jpegger-1.0.0.dist-info/LICENSE
jpegger-1.0.0.dist-info/METADATA
jpegger-1.0.0.dist-info/WHEEL
jpegger-1.0.0.dist-info/entry_points.txt
jpegger-1.0.0.dist-info/RECORD
