Metadata-Version: 2.1
Name: jpegger
Version: 1.0.0
Summary: Python Script to optimise images for websites
Home-page: https://github.com/ValentinKolb/jpegger
License: MIT
Keywords: cli,image,optimisation,web
Author: valentinkolb
Author-email: mail@valentin-kolb.com
Requires-Python: >=3.10,<4.0
Classifier: Environment :: Console
Classifier: License :: OSI Approved :: MIT License
Classifier: Operating System :: OS Independent
Classifier: Programming Language :: Python :: 3
Classifier: Programming Language :: Python :: 3.10
Classifier: Programming Language :: Python :: 3.11
Classifier: Programming Language :: Python :: 3.12
Classifier: Programming Language :: Python :: 3.13
Requires-Dist: click (>=8.1.7,<9.0.0)
Requires-Dist: piexif (>=1.1.3,<2.0.0)
Requires-Dist: pillow (>=11.0.0,<12.0.0)
